polecat/__init__.py
polecat/browser.py
polecat/calendar_gen.py
polecat/config.py
polecat/main.py
polecat/parsers.py
polecat/scrapers.py
jbs_polecat-1.0.0.dist-info/METADATA
jbs_polecat-1.0.0.dist-info/WHEEL
jbs_polecat-1.0.0.dist-info/entry_points.txt
jbs_polecat-1.0.0.dist-info/licenses/LICENSE
jbs_polecat-1.0.0.dist-info/RECORD
