Metadata-Version: 2.4
Name: jbs-polecat
Version: 1.0.0
Summary: Extract exam dates and deadlines from Cambridge Judge Business School learning platform and generate calendar files
Project-URL: Homepage, https://github.com/shoaib-akhter/polecat
Project-URL: Repository, https://github.com/shoaib-akhter/polecat
Project-URL: Issues, https://github.com/shoaib-akhter/polecat/issues
Author: Shoaib Akhter
License-Expression: MIT
License-File: LICENSE
Keywords: automation,calendar,cambridge,ics,jbs,moodle
Classifier: Development Status :: 5 - Production/Stable
Classifier: Environment :: Console
Classifier: Intended Audience :: Education
Classifier: License :: OSI Approved :: MIT License
Classifier: Operating System :: OS Independent
Classifier: Programming Language :: Python :: 3
Classifier: Programming Language :: Python :: 3.10
Classifier: Programming Language :: Python :: 3.11
Classifier: Programming Language :: Python :: 3.12
Classifier: Programming Language :: Python :: 3.13
Classifier: Topic :: Education
Classifier: Topic :: Utilities
Requires-Python: >=3.10
Requires-Dist: beautifulsoup4>=4.12.0
Requires-Dist: dateparser>=1.2.0
Requires-Dist: ics>=0.7.0
Requires-Dist: playwright>=1.40.0
Requires-Dist: pytz>=2023.3
Provides-Extra: dev
Requires-Dist: build>=1.0.0; extra == 'dev'
Requires-Dist: pytest>=7.0.0; extra == 'dev'
Requires-Dist: twine>=4.0.0; extra == 'dev'
